{
  "simulation/beginTimeAsString": "2016/07/16 19:55:47",
  "simulation/endTimeAsString": "2016/07/16 19:56:07",
  "simulation/duration": "0:00:19.928",
  "simulation/durationInSeconds": "19",
  "simulation/cycleAccurateEventQueue/currentCycle": "20077",
  "noc/routerCongestionStatusPredictionHelper/routerCongestionStatusPredictor/numHits": "1284608",
  "noc/routerCongestionStatusPredictionHelper/routerCongestionStatusPredictor/numMisses": "320",
  "noc/routerCongestionStatusPredictionHelper/routerCongestionStatusPredictor/numAccesses": "1284928",
  "noc/routerCongestionStatusPredictionHelper/routerCongestionStatusPredictor/hitRatio": "0.9997509588085869",
  "noc/routerCongestionStatusPredictionHelper/routerCongestionStatusPredictor/coverage": "0.9997510208146599",
  "noc/routerCongestionStatusPredictionHelper/routerCongestionStatusPredictor/accuracy": "0.9997509588085869",
  "noc/numPacketsReceived": "57713",
  "noc/numPacketsTransmitted": "57713",
  "noc/throughput": "0.044915357125068486",
  "noc/averagePacketDelay": "39.073449656056695",
  "noc/averagePacketHops": "6.323583941226413",
  "noc/maxPacketDelay": "97",
  "noc/maxPacketHops": "15",
  "noc/numPayloadPacketsReceived": "57713",
  "noc/numPayloadPacketsTransmitted": "57713",
  "noc/payloadThroughput": "0.044915357125068486",
  "noc/averagePayloadPacketDelay": "39.073449656056695",
  "noc/averagePayloadPacketHops": "6.323583941226413",
  "noc/maxPayloadPacketDelay": "97",
  "noc/maxPayloadPacketHops": "15",
  "noc/averageFlitPerStateDelay::INPUT_BUFFER": "2.3012387896523663",
  "noc/averageFlitPerStateDelay::ROUTE_COMPUTATION": "1.0215753809394634",
  "noc/averageFlitPerStateDelay::VIRTUAL_CHANNEL_ALLOCATION": "1.073034061920302",
  "noc/averageFlitPerStateDelay::SWITCH_ALLOCATION": "1.0",
  "noc/averageFlitPerStateDelay::SWITCH_TRAVERSAL": "1.0",
  "noc/averageFlitPerStateDelay::LINK_TRAVERSAL": "1.0024231870850149",
  "noc/averageFlitPerStateDelay::DESTINATION_ARRIVED": "0.0",
  "noc/maxFlitPerStateDelay::INPUT_BUFFER": "28",
  "noc/maxFlitPerStateDelay::ROUTE_COMPUTATION": "22",
  "noc/maxFlitPerStateDelay::VIRTUAL_CHANNEL_ALLOCATION": "4",
  "noc/maxFlitPerStateDelay::SWITCH_ALLOCATION": "1",
  "noc/maxFlitPerStateDelay::SWITCH_TRAVERSAL": "1",
  "noc/maxFlitPerStateDelay::LINK_TRAVERSAL": "14",
  "noc/maxFlitPerStateDelay::DESTINATION_ARRIVED": "0.0"
}