{
  "simulation/beginTimeAsString": "2016/07/16 19:55:26",
  "simulation/endTimeAsString": "2016/07/16 19:55:47",
  "simulation/duration": "0:00:21.070",
  "simulation/durationInSeconds": "21",
  "simulation/cycleAccurateEventQueue/currentCycle": "20071",
  "noc/routerCongestionStatusPredictionHelper/routerCongestionStatusPredictor/numHits": "1284224",
  "noc/routerCongestionStatusPredictionHelper/routerCongestionStatusPredictor/numMisses": "320",
  "noc/routerCongestionStatusPredictionHelper/routerCongestionStatusPredictor/numAccesses": "1284544",
  "noc/routerCongestionStatusPredictionHelper/routerCongestionStatusPredictor/hitRatio": "0.9997508843605202",
  "noc/routerCongestionStatusPredictionHelper/routerCongestionStatusPredictor/coverage": "0.999750946403666",
  "noc/routerCongestionStatusPredictionHelper/routerCongestionStatusPredictor/accuracy": "0.9997508843605202",
  "noc/numPacketsReceived": "57841",
  "noc/numPacketsTransmitted": "57841",
  "noc/throughput": "0.045028430322355636",
  "noc/averagePacketDelay": "39.26797600318113",
  "noc/averagePacketHops": "6.310247056586158",
  "noc/maxPacketDelay": "96",
  "noc/maxPacketHops": "15",
  "noc/numPayloadPacketsReceived": "57841",
  "noc/numPayloadPacketsTransmitted": "57841",
  "noc/payloadThroughput": "0.045028430322355636",
  "noc/averagePayloadPacketDelay": "39.26797600318113",
  "noc/averagePayloadPacketHops": "6.310247056586158",
  "noc/maxPayloadPacketDelay": "96",
  "noc/maxPayloadPacketHops": "15",
  "noc/averageFlitPerStateDelay::INPUT_BUFFER": "2.3320198306259607",
  "noc/averageFlitPerStateDelay::ROUTE_COMPUTATION": "1.036458433221641",
  "noc/averageFlitPerStateDelay::VIRTUAL_CHANNEL_ALLOCATION": "1.0879418944576715",
  "noc/averageFlitPerStateDelay::SWITCH_ALLOCATION": "1.0",
  "noc/averageFlitPerStateDelay::SWITCH_TRAVERSAL": "1.0",
  "noc/averageFlitPerStateDelay::LINK_TRAVERSAL": "1.0033672472733193",
  "noc/averageFlitPerStateDelay::DESTINATION_ARRIVED": "0.0",
  "noc/maxFlitPerStateDelay::INPUT_BUFFER": "34",
  "noc/maxFlitPerStateDelay::ROUTE_COMPUTATION": "28",
  "noc/maxFlitPerStateDelay::VIRTUAL_CHANNEL_ALLOCATION": "5",
  "noc/maxFlitPerStateDelay::SWITCH_ALLOCATION": "1",
  "noc/maxFlitPerStateDelay::SWITCH_TRAVERSAL": "1",
  "noc/maxFlitPerStateDelay::LINK_TRAVERSAL": "23",
  "noc/maxFlitPerStateDelay::DESTINATION_ARRIVED": "0.0"
}